arctix/__init__.py
arctix/dataset/__init__.py
arctix/dataset/breakfast.py
arctix/dataset/ego4d.py
arctix/dataset/epic_kitchen_100.py
arctix/dataset/multithumos.py
arctix/testing/__init__.py
arctix/testing/fixtures.py
arctix/transformer/__init__.py
arctix/transformer/dataframe/__init__.py
arctix/transformer/dataframe/base.py
arctix/transformer/dataframe/casting.py
arctix/transformer/dataframe/diff.py
arctix/transformer/dataframe/function.py
arctix/transformer/dataframe/json.py
arctix/transformer/dataframe/replace.py
arctix/transformer/dataframe/sequential.py
arctix/transformer/dataframe/sorting.py
arctix/transformer/dataframe/string.py
arctix/transformer/dataframe/time.py
arctix/transformer/dataframe/vocab.py
arctix/utils/__init__.py
arctix/utils/dataframe/__init__.py
arctix/utils/dataframe/removing.py
arctix/utils/dataframe/vocab.py
arctix/utils/download.py
arctix/utils/imports.py
arctix/utils/iter/__init__.py
arctix/utils/iter/path.py
arctix/utils/mapping.py
arctix/utils/masking.py
arctix/utils/ngram.py
arctix/utils/noop.py
arctix/utils/vocab.py
arctix-0.0.8.dist-info/LICENSE
arctix-0.0.8.dist-info/METADATA
arctix-0.0.8.dist-info/WHEEL
arctix-0.0.8.dist-info/RECORD
