Metadata-Version: 2.1
Name: arctix
Version: 0.0.8
Summary: 
Home-page: https://github.com/durandtibo/arctix
License: BSD-3-Clause
Keywords: asynchronous time-series,dataset,preprocessing
Author: Thibaut Durand
Author-email: durand.tibo+gh@gmail.com
Requires-Python: >=3.9,<3.14
Classifier: Development Status :: 3 - Alpha
Classifier: Intended Audience :: Developers
Classifier: Intended Audience :: Science/Research
Classifier: License :: OSI Approved :: BSD License
Classifier: Operating System :: POSIX :: Linux
Classifier: Programming Language :: Python :: 3
Classifier: Programming Language :: Python :: 3.9
Classifier: Programming Language :: Python :: 3.10
Classifier: Programming Language :: Python :: 3.11
Classifier: Programming Language :: Python :: 3.12
Classifier: Programming Language :: Python :: 3.13
Classifier: Topic :: Scientific/Engineering :: Artificial Intelligence
Provides-Extra: all
Requires-Dist: batcharray (>=0.1,<1.0)
Requires-Dist: coola (>=0.8.4,<1.0)
Requires-Dist: gdown (>=5.0,<6.0) ; extra == "all"
Requires-Dist: grizz (>=0.1,<1.0)
Requires-Dist: iden (>=0.1,<1.0)
Requires-Dist: matplotlib (>=3.6,<4.0) ; extra == "all"
Requires-Dist: numpy (>=1.22,<3.0)
Requires-Dist: polars (>=1.0,<2.0)
Requires-Dist: requests (>=2.26,<3.0) ; extra == "all"
Requires-Dist: tqdm (>=4.65,<5.0) ; extra == "all"
Project-URL: Repository, https://github.com/durandtibo/arctix
